poetry_demo_winter/__init__.py
poetry_demo_winter/numlookupapi.py
poetry_demo_winter/validate.py
poetry_demo_winter-0.1.0.dist-info/entry_points.txt
poetry_demo_winter-0.1.0.dist-info/METADATA
poetry_demo_winter-0.1.0.dist-info/WHEEL
poetry_demo_winter-0.1.0.dist-info/RECORD
